pylabhub/__init__.py
pylabhub/adapters/__init__.py
pylabhub/connectors/__init__.py
pylabhub/hub/__init__.py
pylabhub/hub/manifest.py
pylabhub-0.0.1a0.dist-info/licenses/LICENSE
pylabhub-0.0.1a0.dist-info/METADATA
pylabhub-0.0.1a0.dist-info/WHEEL
pylabhub-0.0.1a0.dist-info/entry_points.txt
pylabhub-0.0.1a0.dist-info/top_level.txt
pylabhub-0.0.1a0.dist-info/RECORD
