Metadata-Version: 2.4
Name: pylabhub
Version: 0.0.1a0
Summary: Modular hub for lab data acquisition, control, and reproducible persistence
Author: Quan Qing
License: BSD 3-Clause License
Project-URL: Homepage, https://github.com/Qing-LAB/pylabhub
Requires-Python: >=3.9
License-File: LICENSE
Requires-Dist: pyyaml>=6.0
Dynamic: license-file
